stockroom/__init__.py
stockroom/cli.py
stockroom/core.py
stockroom/keeper.py
stockroom/parser.py
stockroom/utils.py
stockroom/external/__init__.py
stockroom/external/importer/__init__.py
stockroom/external/importer/base.py
stockroom/external/importer/torchvision_importers.py
stockroom/external/importer/utils.py
stockroom/storages/__init__.py
stockroom/storages/data.py
stockroom/storages/experiment.py
stockroom/storages/model.py
stockroom-0.2.2.dist-info/LICENSE
stockroom-0.2.2.dist-info/METADATA
stockroom-0.2.2.dist-info/WHEEL
stockroom-0.2.2.dist-info/entry_points.txt
stockroom-0.2.2.dist-info/top_level.txt
stockroom-0.2.2.dist-info/RECORD
