Metadata-Version: 2.1
Name: stockroom
Version: 0.2.2
Summary: Platform to version model, data, parameters alongside git versioned source code
Home-page: https://github.com/tensorwerk/stockroom
Author: Sherin Thomas
Author-email: sherin@tensorwerk.com
License: Apache Software License 2.0
Project-URL: Documentation, https://stockroom.readthedocs.io
Project-URL: Issue Tracker, https://github.com/tensorwerk/stockroom/issues
Keywords: stockroom
Platform: UNKNOWN
Classifier: Development Status :: 3 - Alpha
Classifier: Intended Audience :: Developers
Classifier: License :: OSI Approved :: Apache Software License
Classifier: Natural Language :: English
Classifier: Operating System :: Microsoft :: Windows
Classifier: Operating System :: POSIX
Classifier: Operating System :: Unix
Classifier: Programming Language :: Python :: 3 :: Only
Classifier: Programming Language :: Python :: 3
Classifier: Programming Language :: Python :: 3.6
Classifier: Programming Language :: Python :: 3.7
Classifier: Topic :: Database
Classifier: Topic :: Scientific/Engineering
Classifier: Topic :: Utilities
Requires-Python: >=3.6
Requires-Dist: Click (>=7.0)
Requires-Dist: click-didyoumean
Requires-Dist: hangar (>=0.5.0)
